chaeto/cli.py
chaeto-0.0.2.dist-info/METADATA
chaeto-0.0.2.dist-info/WHEEL
chaeto-0.0.2.dist-info/entry_points.txt
chaeto-0.0.2.dist-info/licenses/LICENSE
chaeto-0.0.2.dist-info/RECORD
